subprocess_view/__init__.py
subprocess_view/apps.py
subprocess_view/urls.py
subprocess_view/views.py
django_subprocess_view-0.0.0.dist-info/LICENSE
django_subprocess_view-0.0.0.dist-info/METADATA
django_subprocess_view-0.0.0.dist-info/WHEEL
django_subprocess_view-0.0.0.dist-info/top_level.txt
django_subprocess_view-0.0.0.dist-info/RECORD
