Metadata-Version: 2.1
Name: django-subprocess-view
Version: 0.0.0
Summary: An app for a superuser to run subprocess commands in a Django project
Author-email: Rami <ramiboutas@protonmail.com>
Project-URL: Homepage, https://github.com/ramiboutas/django-subprocess-view
Project-URL: Bug Tracker, https://github.com/ramiboutas/django-subprocess-view/issues
Classifier: Programming Language :: Python :: 3
Classifier: License :: OSI Approved :: MIT License
Classifier: Operating System :: OS Independent
Classifier: Framework :: Django
Classifier: Framework :: Django :: 4
Requires-Python: >=3.7
License-File: LICENSE
Requires-Dist: django
